securely/__init__.py
securely/auth.py
securely-0.1.9.dist-info/METADATA
securely-0.1.9.dist-info/WHEEL
securely-0.1.9.dist-info/top_level.txt
securely-0.1.9.dist-info/RECORD
