Metadata-Version: 2.1
Name: securely
Version: 0.1.9
Summary: This package will help you while authorization and authentication in fastapi
Home-page: https://github.com/coderxuz/securely
Author: Xursand
Author-email: coderxuz2009@gmail.com
Classifier: Programming Language :: Python :: 3
Classifier: License :: OSI Approved :: MIT License
Classifier: Operating System :: OS Independent
Requires-Python: >=3.6
Requires-Dist: passlib
Requires-Dist: authlib
Requires-Dist: bcrypt
